bbox/__init__.py
bbox/coco.py
bbox/utils.py
bbox/version.py
bbox_utility-1.0.13.dist-info/LICENSE.md
bbox_utility-1.0.13.dist-info/METADATA
bbox_utility-1.0.13.dist-info/WHEEL
bbox_utility-1.0.13.dist-info/top_level.txt
bbox_utility-1.0.13.dist-info/RECORD
