Metadata-Version: 2.1
Name: bbox-utility
Version: 1.0.13
Summary: BBox Utility for Object Detection & Instance Segmentation. https://github.com/awsaf49/bbox
Home-page: https://github.com/awsaf49/bbox
Author: Awsaf
Author-email: awsaf49@gmail.com
License: MIT
Keywords: bbox utility for object detection & instance segmentation
Platform: UNKNOWN
Classifier: Development Status :: 3 - Alpha
Classifier: Intended Audience :: Developers
Classifier: Intended Audience :: Science/Research
Classifier: License :: OSI Approved :: Apache Software License
Classifier: Programming Language :: Python :: 3.6
Classifier: Programming Language :: Python :: 3.7
Classifier: Programming Language :: Python :: 3.8
Classifier: Topic :: Scientific/Engineering
Classifier: Topic :: Scientific/Engineering :: Artificial Intelligence
Classifier: Topic :: Software Development
Classifier: Topic :: Software Development :: Libraries
Classifier: Topic :: Software Development :: Libraries :: Python Modules
Requires-Python: >=3.6
License-File: LICENSE.md
Requires-Dist: numpy
Requires-Dist: pandas
Requires-Dist: tqdm
Requires-Dist: numba (>=0.54.0)
Requires-Dist: joblib
Requires-Dist: loguru
